{
  "tags": null,
  "ignoreAlpha": false,
  "maxSimultaneousLights": 4,
  "mode": 0,
  "forceAlphaBlending": false,
  "id": "fangzi_002_Baked_mat",
  "name": "fangzi_002_Baked_mat",
  "checkReadyOnEveryCall": false,
  "checkReadyOnlyOnce": false,
  "state": "",
  "alpha": 1,
  "backFaceCulling": true,
  "cullBackFaces": true,
  "sideOrientation": 1,
  "alphaMode": 2,
  "_needDepthPrePass": false,
  "disableDepthWrite": false,
  "disableColorWrite": false,
  "forceDepthWrite": false,
  "depthFunction": 0,
  "separateCullingPass": false,
  "fogEnabled": true,
  "pointSize": 1,
  "zOffset": 0,
  "zOffsetUnits": 0,
  "pointsCloud": false,
  "fillMode": 0,
  "transparencyMode": 1,
  "editorData": {
    "locations": [
      {
        "blockId": 1079,
        "x": 980,
        "y": -1220
      },
      {
        "blockId": 1080,
        "x": 740,
        "y": -1240
      },
      {
        "blockId": 1081,
        "x": 420,
        "y": -1300
      },
      {
        "blockId": 1082,
        "x": 80,
        "y": -1500
      },
      {
        "blockId": 1083,
        "x": -880,
        "y": -1620
      },
      {
        "blockId": 1084,
        "x": -920,
        "y": -1460
      },
      {
        "blockId": 1085,
        "x": -960,
        "y": -1160
      },
      {
        "blockId": 1086,
        "x": -480,
        "y": -1380
      },
      {
        "blockId": 1087,
        "x": 80,
        "y": -1260
      },
      {
        "blockId": 1088,
        "x": -720,
        "y": -2000
      },
      {
        "blockId": 1089,
        "x": -720,
        "y": -1800
      },
      {
        "blockId": 1090,
        "x": -640,
        "y": -980
      },
      {
        "blockId": 1091,
        "x": -1000,
        "y": -980
      },
      {
        "blockId": 1092,
        "x": -1000,
        "y": -880
      },
      {
        "blockId": 1093,
        "x": -1000,
        "y": -780
      },
      {
        "blockId": 1094,
        "x": -1000,
        "y": -680
      },
      {
        "blockId": 1095,
        "x": -1000,
        "y": -580
      },
      {
        "blockId": 1096,
        "x": 420,
        "y": -1140
      },
      {
        "blockId": 1097,
        "x": 5240,
        "y": -20
      },
      {
        "blockId": 1098,
        "x": 4840,
        "y": 60
      },
      {
        "blockId": 1099,
        "x": 4480,
        "y": 80
      },
      {
        "blockId": 1100,
        "x": 3900,
        "y": -20
      },
      {
        "blockId": 1101,
        "x": 2840,
        "y": -240
      },
      {
        "blockId": 1102,
        "x": -1740,
        "y": 1340
      },
      {
        "blockId": 1104,
        "x": 3520,
        "y": 40
      },
      {
        "blockId": 1105,
        "x": 3240,
        "y": 40
      },
      {
        "blockId": 1106,
        "x": 2940,
        "y": 120
      },
      {
        "blockId": 1107,
        "x": 2580,
        "y": 120
      },
      {
        "blockId": 1108,
        "x": 2600,
        "y": 240
      },
      {
        "blockId": 1109,
        "x": 2320,
        "y": 240
      },
      {
        "blockId": 1110,
        "x": 1660,
        "y": 2860
      },
      {
        "blockId": 1111,
        "x": 1460,
        "y": 2860
      },
      {
        "blockId": 1112,
        "x": 1040,
        "y": 2880
      },
      {
        "blockId": 1113,
        "x": 160,
        "y": 3920
      },
      {
        "blockId": 1114,
        "x": -240,
        "y": 3860
      },
      {
        "blockId": 1115,
        "x": -200,
        "y": 3700
      },
      {
        "blockId": 1116,
        "x": -1780,
        "y": 2860
      },
      {
        "blockId": 1117,
        "x": -1740,
        "y": 1820
      },
      {
        "blockId": 1119,
        "x": 120,
        "y": 4220
      },
      {
        "blockId": 1120,
        "x": -1780,
        "y": 3000
      },
      {
        "blockId": 1121,
        "x": 780,
        "y": 2840
      },
      {
        "blockId": 1122,
        "x": -1780,
        "y": 2320
      },
      {
        "blockId": 1123,
        "x": 160,
        "y": 2820
      },
      {
        "blockId": 1124,
        "x": -120,
        "y": 2820
      },
      {
        "blockId": 1125,
        "x": -520,
        "y": 2700
      },
      {
        "blockId": 1126,
        "x": -1740,
        "y": 1580
      },
      {
        "blockId": 1128,
        "x": -1780,
        "y": 2440
      },
      {
        "blockId": 1129,
        "x": -120,
        "y": 2680
      },
      {
        "blockId": 1130,
        "x": 460,
        "y": 3040
      },
      {
        "blockId": 1131,
        "x": 400,
        "y": 3200
      },
      {
        "blockId": 1132,
        "x": 2260,
        "y": 360
      },
      {
        "blockId": 1133,
        "x": 2560,
        "y": 360
      },
      {
        "blockId": 1134,
        "x": 3500,
        "y": 180
      },
      {
        "blockId": 1135,
        "x": 3380,
        "y": 820
      },
      {
        "blockId": 1136,
        "x": 3000,
        "y": 820
      },
      {
        "blockId": 1137,
        "x": 2620,
        "y": 820
      },
      {
        "blockId": 1138,
        "x": 2340,
        "y": 800
      },
      {
        "blockId": 1139,
        "x": 2060,
        "y": 800
      },
      {
        "blockId": 1140,
        "x": 1620,
        "y": 780
      },
      {
        "blockId": 1141,
        "x": 1160,
        "y": 760
      },
      {
        "blockId": 1142,
        "x": 420,
        "y": -1020
      },
      {
        "blockId": 1143,
        "x": 780,
        "y": 840
      },
      {
        "blockId": 1144,
        "x": 520,
        "y": 820
      },
      {
        "blockId": 1145,
        "x": 480,
        "y": 980
      },
      {
        "blockId": 1146,
        "x": 1920,
        "y": 2860
      },
      {
        "blockId": 1147,
        "x": 1180,
        "y": 900
      },
      {
        "blockId": 1148,
        "x": 1960,
        "y": 1060
      },
      {
        "blockId": 1149,
        "x": 1680,
        "y": 1060
      },
      {
        "blockId": 1150,
        "x": 1180,
        "y": 1020
      },
      {
        "blockId": 1151,
        "x": 2340,
        "y": 960
      },
      {
        "blockId": 1152,
        "x": -1780,
        "y": 2080
      },
      {
        "blockId": 1153,
        "x": 2700,
        "y": 1440
      },
      {
        "blockId": 1154,
        "x": -1780,
        "y": 2200
      },
      {
        "blockId": 1155,
        "x": 2200,
        "y": 1440
      },
      {
        "blockId": 1156,
        "x": 1800,
        "y": 1420
      },
      {
        "blockId": 1157,
        "x": 1780,
        "y": 1320
      },
      {
        "blockId": 1158,
        "x": 1300,
        "y": 1380
      },
      {
        "blockId": 1159,
        "x": 980,
        "y": 1380
      },
      {
        "blockId": 1160,
        "x": 1260,
        "y": 1500
      },
      {
        "blockId": 1161,
        "x": 2340,
        "y": 1760
      },
      {
        "blockId": 1162,
        "x": 2000,
        "y": 1760
      },
      {
        "blockId": 1163,
        "x": 1720,
        "y": 1760
      },
      {
        "blockId": 1164,
        "x": 1420,
        "y": 1760
      },
      {
        "blockId": 1165,
        "x": 1120,
        "y": 1880
      },
      {
        "blockId": 1166,
        "x": 720,
        "y": 1900
      },
      {
        "blockId": 1167,
        "x": 740,
        "y": 2000
      },
      {
        "blockId": 1168,
        "x": 740,
        "y": 2100
      },
      {
        "blockId": 1169,
        "x": 1680,
        "y": 1880
      },
      {
        "blockId": 1170,
        "x": 1960,
        "y": 1880
      },
      {
        "blockId": 1171,
        "x": -1780,
        "y": 2720
      },
      {
        "blockId": 1172,
        "x": 180,
        "y": 4920
      },
      {
        "blockId": 1173,
        "x": 140,
        "y": 4820
      },
      {
        "blockId": 1174,
        "x": -240,
        "y": 4960
      },
      {
        "blockId": 1175,
        "x": -500,
        "y": 4960
      },
      {
        "blockId": 1176,
        "x": -540,
        "y": 5080
      },
      {
        "blockId": 1177,
        "x": -1780,
        "y": 2580
      },
      {
        "blockId": 5087,
        "x": 240,
        "y": 3600
      }
    ],
    "frames": [
      {
        "x": -640,
        "y": 4540,
        "width": 1421.33,
        "height": 700,
        "color": [
          0.2823529411764706,
          0.2823529411764706,
          0.2823529411764706
        ],
        "name": "AO",
        "isCollapsed": false,
        "blocks": [
          1172,
          1173,
          1174,
          1175,
          1176
        ]
      },
      {
        "x": -620,
        "y": 3540,
        "width": 1131.38,
        "height": 820,
        "color": [
          0.2823529411764706,
          0.2823529411764706,
          0.2823529411764706
        ],
        "name": "detail",
        "isCollapsed": false,
        "blocks": [
          1113,
          1114,
          1119,
          1115,
          5087
        ]
      },
      {
        "x": -640,
        "y": 2440,
        "width": 2780.84,
        "height": 940,
        "color": [
          0.2823529411764706,
          0.2823529411764706,
          0.2823529411764706
        ],
        "name": "rough",
        "isCollapsed": false,
        "blocks": [
          1110,
          1121,
          1111,
          1130,
          1112,
          1123,
          1124,
          1129,
          1125,
          1131,
          1146
        ]
      },
      {
        "x": 413.8893487213252,
        "y": 606.636462645985,
        "width": 2484.53,
        "height": 620,
        "color": [
          0.2823529411764706,
          0.2823529411764706,
          0.2823529411764706
        ],
        "name": "front",
        "isCollapsed": false,
        "blocks": [
          1138,
          1151,
          1137,
          1141,
          1147,
          1143,
          1144,
          1145,
          1140,
          1139,
          1149,
          1148,
          1150
        ]
      },
      {
        "x": 900.927,
        "y": 1273.53,
        "width": 2079.08,
        "height": 340,
        "color": [
          0.2823529411764706,
          0.2823529411764706,
          0.2823529411764706
        ],
        "name": "rim",
        "isCollapsed": false,
        "blocks": [
          1153,
          1155,
          1156,
          1157,
          1159,
          1158,
          1160
        ]
      },
      {
        "x": 580,
        "y": 1680,
        "width": 2122.4,
        "height": 560,
        "color": [
          0.2823529411764706,
          0.2823529411764706,
          0.2823529411764706
        ],
        "name": "top",
        "isCollapsed": false,
        "blocks": [
          1161,
          1162,
          1163,
          1170,
          1164,
          1169,
          1165,
          1166,
          1167,
          1168
        ]
      },
      {
        "x": 2160,
        "y": -360,
        "width": 2040.92,
        "height": 840,
        "color": [
          0.2823529411764706,
          0.2823529411764706,
          0.2823529411764706
        ],
        "name": "lighting",
        "isCollapsed": false,
        "blocks": [
          1100,
          1101,
          1104,
          1105,
          1106,
          1107,
          1108,
          1109,
          1133,
          1132,
          1134
        ]
      },
      {
        "x": -1840,
        "y": 1260,
        "width": 391.272,
        "height": 1920,
        "color": [
          0.2823529411764706,
          0.2823529411764706,
          0.2823529411764706
        ],
        "name": "input",
        "isCollapsed": false,
        "blocks": [
          1102,
          1122,
          1117,
          1116,
          1120,
          1128,
          1126,
          1152,
          1154,
          1171,
          1177
        ]
      }
    ],
    "x": 1461.4676041929686,
    "y": -181.88267678305425,
    "zoom": 0.24190893746872774
  },
  "customType": "BABYLON.NodeMaterial",
  "outputNodes": [
    1079,
    1097
  ],
  "blocks": [
    {
      "customType": "BABYLON.VertexOutputBlock",
      "id": 1079,
      "name": "VertexOutput",
      "comments": "",
      "visibleInInspector": false,
      "visibleOnFrame": false,
      "target": 1,
      "inputs": [
        {
          "name": "vector",
          "inputName": "vector",
          "targetBlockId": 1080,
          "targetConnectionName": "output",
          "isExposedOnFrame": true,
          "exposedPortPosition": -1
        }
      ],
      "outputs": []
    },
    {
      "customType": "BABYLON.TransformBlock",
      "id": 1080,
      "name": "WorldPos * ViewProjectionTransform",
      "comments": "",
      "visibleInInspector": false,
      "visibleOnFrame": false,
      "target": 1,
      "inputs": [
        {
          "name": "vector",
          "inputName": "vector",
          "targetBlockId": 1081,
          "targetConnectionName": "output",
          "isExposedOnFrame": true,
          "exposedPortPosition": -1
        },
        {
          "name": "transform",
          "inputName": "transform",
          "targetBlockId": 1096,
          "targetConnectionName": "output",
          "isExposedOnFrame": true,
          "exposedPortPosition": -1
        }
      ],
      "outputs": [
        {
          "name": "output"
        },
        {
          "name": "xyz"
        }
      ],
      "complementZ": 0,
      "complementW": 1
    },
    {
      "customType": "BABYLON.TransformBlock",
      "id": 1081,
      "name": "WorldPos",
      "comments": "",
      "visibleInInspector": false,
      "visibleOnFrame": false,
      "target": 1,
      "inputs": [
        {
          "name": "vector",
          "inputName": "vector",
          "targetBlockId": 1082,
          "targetConnectionName": "positionOutput",
          "isExposedOnFrame": true,
          "exposedPortPosition": -1
        },
        {
          "name": "transform",
          "inputName": "transform",
          "targetBlockId": 1087,
          "targetConnectionName": "output",
          "isExposedOnFrame": true,
          "exposedPortPosition": -1
        }
      ],
      "outputs": [
        {
          "name": "output"
        },
        {
          "name": "xyz"
        }
      ],
      "complementZ": 0,
      "complementW": 1
    },
    {
      "customType": "BABYLON.MorphTargetsBlock",
      "id": 1082,
      "name": "MorphTargets",
      "comments": "",
      "visibleInInspector": false,
      "visibleOnFrame": false,
      "target": 1,
      "inputs": [
        {
          "name": "position",
          "inputName": "position",
          "targetBlockId": 1083,
          "targetConnectionName": "output",
          "isExposedOnFrame": true,
          "exposedPortPosition": -1
        },
        {
          "name": "normal",
          "inputName": "normal",
          "targetBlockId": 1084,
          "targetConnectionName": "output",
          "isExposedOnFrame": true,
          "exposedPortPosition": -1
        },
        {
          "name": "tangent",
          "inputName": "tangent",
          "targetBlockId": 1085,
          "targetConnectionName": "output",
          "isExposedOnFrame": true,
          "exposedPortPosition": -1
        },
        {
          "name": "uv",
          "inputName": "uv",
          "targetBlockId": 1086,
          "targetConnectionName": "output",
          "isExposedOnFrame": true,
          "exposedPortPosition": -1
        }
      ],
      "outputs": [
        {
          "name": "positionOutput"
        },
        {
          "name": "normalOutput"
        },
        {
          "name": "tangentOutput"
        },
        {
          "name": "uvOutput"
        }
      ]
    },
    {
      "customType": "BABYLON.InputBlock",
      "id": 1083,
      "name": "position",
      "comments": "",
      "visibleInInspector": false,
      "visibleOnFrame": false,
      "target": 1,
      "inputs": [],
      "outputs": [
        {
          "name": "output"
        }
      ],
      "type": 8,
      "mode": 1,
      "animationType": 0,
      "min": 0,
      "max": 0,
      "isBoolean": false,
      "matrixMode": 0,
      "isConstant": false,
      "groupInInspector": "",
      "convertToGammaSpace": false,
      "convertToLinearSpace": false
    },
    {
      "customType": "BABYLON.InputBlock",
      "id": 1084,
      "name": "normal",
      "comments": "",
      "visibleInInspector": false,
      "visibleOnFrame": false,
      "target": 1,
      "inputs": [],
      "outputs": [
        {
          "name": "output"
        }
      ],
      "type": 8,
      "mode": 1,
      "animationType": 0,
      "min": 0,
      "max": 0,
      "isBoolean": false,
      "matrixMode": 0,
      "isConstant": false,
      "groupInInspector": "",
      "convertToGammaSpace": false,
      "convertToLinearSpace": false
    },
    {
      "customType": "BABYLON.InputBlock",
      "id": 1085,
      "name": "tangent",
      "comments": "",
      "visibleInInspector": false,
      "visibleOnFrame": false,
      "target": 1,
      "inputs": [],
      "outputs": [
        {
          "name": "output"
        }
      ],
      "type": 16,
      "mode": 1,
      "animationType": 0,
      "min": 0,
      "max": 0,
      "isBoolean": false,
      "matrixMode": 0,
      "isConstant": false,
      "groupInInspector": "",
      "convertToGammaSpace": false,
      "convertToLinearSpace": false
    },
    {
      "customType": "BABYLON.InputBlock",
      "id": 1086,
      "name": "uv",
      "comments": "",
      "visibleInInspector": false,
      "visibleOnFrame": false,
      "target": 1,
      "inputs": [],
      "outputs": [
        {
          "name": "output"
        }
      ],
      "type": 4,
      "mode": 1,
      "animationType": 0,
      "min": 0,
      "max": 0,
      "isBoolean": false,
      "matrixMode": 0,
      "isConstant": false,
      "groupInInspector": "",
      "convertToGammaSpace": false,
      "convertToLinearSpace": false
    },
    {
      "customType": "BABYLON.BonesBlock",
      "id": 1087,
      "name": "Bones",
      "comments": "",
      "visibleInInspector": false,
      "visibleOnFrame": false,
      "target": 1,
      "inputs": [
        {
          "name": "matricesIndices",
          "inputName": "matricesIndices",
          "targetBlockId": 1088,
          "targetConnectionName": "output",
          "isExposedOnFrame": true,
          "exposedPortPosition": -1
        },
        {
          "name": "matricesWeights",
          "inputName": "matricesWeights",
          "targetBlockId": 1089,
          "targetConnectionName": "output",
          "isExposedOnFrame": true,
          "exposedPortPosition": -1
        },
        {
          "name": "matricesIndicesExtra"
        },
        {
          "name": "matricesWeightsExtra"
        },
        {
          "name": "world",
          "inputName": "world",
          "targetBlockId": 1090,
          "targetConnectionName": "output",
          "isExposedOnFrame": true,
          "exposedPortPosition": -1
        }
      ],
      "outputs": [
        {
          "name": "output"
        }
      ]
    },
    {
      "customType": "BABYLON.InputBlock",
      "id": 1088,
      "name": "matricesIndices",
      "comments": "",
      "visibleInInspector": false,
      "visibleOnFrame": false,
      "target": 1,
      "inputs": [],
      "outputs": [
        {
          "name": "output"
        }
      ],
      "type": 16,
      "mode": 1,
      "animationType": 0,
      "min": 0,
      "max": 0,
      "isBoolean": false,
      "matrixMode": 0,
      "isConstant": false,
      "groupInInspector": "",
      "convertToGammaSpace": false,
      "convertToLinearSpace": false
    },
    {
      "customType": "BABYLON.InputBlock",
      "id": 1089,
      "name": "matricesWeights",
      "comments": "",
      "visibleInInspector": false,
      "visibleOnFrame": false,
      "target": 1,
      "inputs": [],
      "outputs": [
        {
          "name": "output"
        }
      ],
      "type": 16,
      "mode": 1,
      "animationType": 0,
      "min": 0,
      "max": 0,
      "isBoolean": false,
      "matrixMode": 0,
      "isConstant": false,
      "groupInInspector": "",
      "convertToGammaSpace": false,
      "convertToLinearSpace": false
    },
    {
      "customType": "BABYLON.InstancesBlock",
      "id": 1090,
      "name": "Instances",
      "comments": "",
      "visibleInInspector": false,
      "visibleOnFrame": false,
      "target": 1,
      "inputs": [
        {
          "name": "world0",
          "inputName": "world0",
          "targetBlockId": 1091,
          "targetConnectionName": "output",
          "isExposedOnFrame": true,
          "exposedPortPosition": -1
        },
        {
          "name": "world1",
          "inputName": "world1",
          "targetBlockId": 1092,
          "targetConnectionName": "output",
          "isExposedOnFrame": true,
          "exposedPortPosition": -1
        },
        {
          "name": "world2",
          "inputName": "world2",
          "targetBlockId": 1093,
          "targetConnectionName": "output",
          "isExposedOnFrame": true,
          "exposedPortPosition": -1
        },
        {
          "name": "world3",
          "inputName": "world3",
          "targetBlockId": 1094,
          "targetConnectionName": "output",
          "isExposedOnFrame": true,
          "exposedPortPosition": -1
        },
        {
          "name": "world",
          "inputName": "world",
          "targetBlockId": 1095,
          "targetConnectionName": "output",
          "isExposedOnFrame": true,
          "exposedPortPosition": -1
        }
      ],
      "outputs": [
        {
          "name": "output"
        },
        {
          "name": "instanceID"
        }
      ]
    },
    {
      "customType": "BABYLON.InputBlock",
      "id": 1091,
      "name": "world0",
      "comments": "",
      "visibleInInspector": false,
      "visibleOnFrame": false,
      "target": 1,
      "inputs": [],
      "outputs": [
        {
          "name": "output"
        }
      ],
      "type": 16,
      "mode": 1,
      "animationType": 0,
      "min": 0,
      "max": 0,
      "isBoolean": false,
      "matrixMode": 0,
      "isConstant": false,
      "groupInInspector": "",
      "convertToGammaSpace": false,
      "convertToLinearSpace": false
    },
    {
      "customType": "BABYLON.InputBlock",
      "id": 1092,
      "name": "world1",
      "comments": "",
      "visibleInInspector": false,
      "visibleOnFrame": false,
      "target": 1,
      "inputs": [],
      "outputs": [
        {
          "name": "output"
        }
      ],
      "type": 16,
      "mode": 1,
      "animationType": 0,
      "min": 0,
      "max": 0,
      "isBoolean": false,
      "matrixMode": 0,
      "isConstant": false,
      "groupInInspector": "",
      "convertToGammaSpace": false,
      "convertToLinearSpace": false
    },
    {
      "customType": "BABYLON.InputBlock",
      "id": 1093,
      "name": "world2",
      "comments": "",
      "visibleInInspector": false,
      "visibleOnFrame": false,
      "target": 1,
      "inputs": [],
      "outputs": [
        {
          "name": "output"
        }
      ],
      "type": 16,
      "mode": 1,
      "animationType": 0,
      "min": 0,
      "max": 0,
      "isBoolean": false,
      "matrixMode": 0,
      "isConstant": false,
      "groupInInspector": "",
      "convertToGammaSpace": false,
      "convertToLinearSpace": false
    },
    {
      "customType": "BABYLON.InputBlock",
      "id": 1094,
      "name": "world3",
      "comments": "",
      "visibleInInspector": false,
      "visibleOnFrame": false,
      "target": 1,
      "inputs": [],
      "outputs": [
        {
          "name": "output"
        }
      ],
      "type": 16,
      "mode": 1,
      "animationType": 0,
      "min": 0,
      "max": 0,
      "isBoolean": false,
      "matrixMode": 0,
      "isConstant": false,
      "groupInInspector": "",
      "convertToGammaSpace": false,
      "convertToLinearSpace": false
    },
    {
      "customType": "BABYLON.InputBlock",
      "id": 1095,
      "name": "world",
      "comments": "",
      "visibleInInspector": false,
      "visibleOnFrame": false,
      "target": 1,
      "inputs": [],
      "outputs": [
        {
          "name": "output"
        }
      ],
      "type": 128,
      "mode": 0,
      "systemValue": 1,
      "animationType": 0,
      "min": 0,
      "max": 0,
      "isBoolean": false,
      "matrixMode": 0,
      "isConstant": false,
      "groupInInspector": "",
      "convertToGammaSpace": false,
      "convertToLinearSpace": false
    },
    {
      "customType": "BABYLON.InputBlock",
      "id": 1096,
      "name": "ViewProjection",
      "comments": "",
      "visibleInInspector": false,
      "visibleOnFrame": false,
      "target": 1,
      "inputs": [],
      "outputs": [
        {
          "name": "output"
        }
      ],
      "type": 128,
      "mode": 0,
      "systemValue": 4,
      "animationType": 0,
      "min": 0,
      "max": 0,
      "isBoolean": false,
      "matrixMode": 0,
      "isConstant": false,
      "groupInInspector": "",
      "convertToGammaSpace": false,
      "convertToLinearSpace": false
    },
    {
      "customType": "BABYLON.FragmentOutputBlock",
      "id": 1097,
      "name": "FragmentOutput",
      "comments": "",
      "visibleInInspector": false,
      "visibleOnFrame": false,
      "target": 2,
      "inputs": [
        {
          "name": "rgba"
        },
        {
          "name": "rgb",
          "inputName": "rgb",
          "targetBlockId": 1098,
          "targetConnectionName": "rgb",
          "isExposedOnFrame": true,
          "exposedPortPosition": -1
        },
        {
          "name": "a"
        }
      ],
      "outputs": [],
      "convertToGammaSpace": false,
      "convertToLinearSpace": false,
      "useLogarithmicDepth": false
    },
    {
      "customType": "BABYLON.ImageProcessingBlock",
      "id": 1098,
      "name": "ImageProcessing",
      "comments": "",
      "visibleInInspector": false,
      "visibleOnFrame": false,
      "target": 2,
      "inputs": [
        {
          "name": "color",
          "inputName": "color",
          "targetBlockId": 1099,
          "targetConnectionName": "output",
          "isExposedOnFrame": true,
          "exposedPortPosition": -1
        }
      ],
      "outputs": [
        {
          "name": "output"
        },
        {
          "name": "rgb"
        }
      ],
      "convertInputToLinearSpace": true
    },
    {
      "customType": "BABYLON.ScaleBlock",
      "id": 1099,
      "name": "Scale",
      "comments": "",
      "visibleInInspector": false,
      "visibleOnFrame": false,
      "target": 4,
      "inputs": [
        {
          "name": "input",
          "inputName": "input",
          "targetBlockId": 1100,
          "targetConnectionName": "output",
          "isExposedOnFrame": true,
          "exposedPortPosition": -1
        },
        {
          "name": "factor",
          "inputName": "factor",
          "targetBlockId": 1172,
          "targetConnectionName": "output",
          "isExposedOnFrame": true,
          "exposedPortPosition": -1
        }
      ],
      "outputs": [
        {
          "name": "output"
        }
      ]
    },
    {
      "customType": "BABYLON.LerpBlock",
      "id": 1100,
      "name": "light",
      "comments": "",
      "visibleInInspector": false,
      "visibleOnFrame": false,
      "target": 4,
      "inputs": [
        {
          "name": "left",
          "inputName": "left",
          "targetBlockId": 1101,
          "targetConnectionName": "rgb",
          "isExposedOnFrame": true,
          "exposedPortPosition": -1
        },
        {
          "name": "right",
          "inputName": "right",
          "targetBlockId": 1104,
          "targetConnectionName": "output",
          "isExposedOnFrame": true,
          "exposedPortPosition": -1
        },
        {
          "name": "gradient",
          "inputName": "gradient",
          "targetBlockId": 1134,
          "targetConnectionName": "output",
          "isExposedOnFrame": true,
          "exposedPortPosition": -1
        }
      ],
      "outputs": [
        {
          "name": "output"
        }
      ]
    },
    {
      "customType": "BABYLON.TextureBlock",
      "id": 1101,
      "name": "Texture",
      "comments": "",
      "visibleInInspector": false,
      "visibleOnFrame": false,
      "target": 3,
      "inputs": [
        {
          "name": "uv",
          "inputName": "uv",
          "targetBlockId": 1086,
          "targetConnectionName": "output",
          "isExposedOnFrame": true,
          "exposedPortPosition": -1
        },
        {
          "name": "source",
          "inputName": "source",
          "targetBlockId": 1102,
          "targetConnectionName": "source",
          "isExposedOnFrame": true,
          "exposedPortPosition": -1
        },
        {
          "name": "layer"
        },
        {
          "name": "lod"
        }
      ],
      "outputs": [
        {
          "name": "rgba"
        },
        {
          "name": "rgb"
        },
        {
          "name": "r"
        },
        {
          "name": "g"
        },
        {
          "name": "b"
        },
        {
          "name": "a"
        },
        {
          "name": "level"
        }
      ],
      "convertToGammaSpace": false,
      "convertToLinearSpace": false,
      "fragmentOnly": false,
      "disableLevelMultiplication": false
    },
    {
      "customType": "BABYLON.ImageSourceBlock",
      "id": 1102,
      "name": "diffuseTexture",
      "comments": "",
      "visibleInInspector": false,
      "visibleOnFrame": false,
      "target": 3,
      "inputs": [],
      "outputs": [
        {
          "name": "source"
        }
      ]
    },
    {
      "customType": "BABYLON.ClampBlock",
      "id": 1104,
      "name": "Clamp",
      "comments": "",
      "visibleInInspector": false,
      "visibleOnFrame": false,
      "target": 4,
      "inputs": [
        {
          "name": "value",
          "inputName": "value",
          "targetBlockId": 1105,
          "targetConnectionName": "output",
          "isExposedOnFrame": true,
          "exposedPortPosition": -1
        }
      ],
      "outputs": [
        {
          "name": "output"
        }
      ],
      "minimum": 0,
      "maximum": 1
    },
    {
      "customType": "BABYLON.ScaleBlock",
      "id": 1105,
      "name": "increase",
      "comments": "",
      "visibleInInspector": false,
      "visibleOnFrame": false,
      "target": 4,
      "inputs": [
        {
          "name": "input",
          "inputName": "input",
          "targetBlockId": 1101,
          "targetConnectionName": "rgb",
          "isExposedOnFrame": true,
          "exposedPortPosition": -1
        },
        {
          "name": "factor",
          "inputName": "factor",
          "targetBlockId": 1106,
          "targetConnectionName": "output",
          "isExposedOnFrame": true,
          "exposedPortPosition": -1
        }
      ],
      "outputs": [
        {
          "name": "output"
        }
      ]
    },
    {
      "customType": "BABYLON.ScaleBlock",
      "id": 1106,
      "name": "Scale",
      "comments": "",
      "visibleInInspector": false,
      "visibleOnFrame": false,
      "target": 4,
      "inputs": [
        {
          "name": "input",
          "inputName": "input",
          "targetBlockId": 1107,
          "targetConnectionName": "output",
          "isExposedOnFrame": true,
          "exposedPortPosition": -1
        },
        {
          "name": "factor",
          "inputName": "factor",
          "targetBlockId": 1108,
          "targetConnectionName": "output",
          "isExposedOnFrame": true,
          "exposedPortPosition": -1
        }
      ],
      "outputs": [
        {
          "name": "output"
        }
      ]
    },
    {
      "customType": "BABYLON.InputBlock",
      "id": 1107,
      "name": "Float",
      "comments": "",
      "visibleInInspector": false,
      "visibleOnFrame": false,
      "target": 1,
      "inputs": [],
      "outputs": [
        {
          "name": "output"
        }
      ],
      "type": 1,
      "mode": 0,
      "animationType": 0,
      "min": 0,
      "max": 0,
      "isBoolean": false,
      "matrixMode": 0,
      "isConstant": true,
      "groupInInspector": "",
      "convertToGammaSpace": false,
      "convertToLinearSpace": false,
      "valueType": "number",
      "value": 2
    },
    {
      "customType": "BABYLON.AddBlock",
      "id": 1108,
      "name": "Add",
      "comments": "",
      "visibleInInspector": false,
      "visibleOnFrame": false,
      "target": 4,
      "inputs": [
        {
          "name": "left",
          "inputName": "left",
          "targetBlockId": 1109,
          "targetConnectionName": "output",
          "isExposedOnFrame": true,
          "exposedPortPosition": -1
        },
        {
          "name": "right",
          "inputName": "right",
          "targetBlockId": 1133,
          "targetConnectionName": "output",
          "isExposedOnFrame": true,
          "exposedPortPosition": -1
        }
      ],
      "outputs": [
        {
          "name": "output"
        }
      ]
    },
    {
      "customType": "BABYLON.ScaleBlock",
      "id": 1109,
      "name": "Scale",
      "comments": "",
      "visibleInInspector": false,
      "visibleOnFrame": false,
      "target": 4,
      "inputs": [
        {
          "name": "input",
          "inputName": "input",
          "targetBlockId": 1110,
          "targetConnectionName": "output",
          "isExposedOnFrame": true,
          "exposedPortPosition": -1
        },
        {
          "name": "factor",
          "inputName": "factor",
          "targetBlockId": 1132,
          "targetConnectionName": "output",
          "isExposedOnFrame": true,
          "exposedPortPosition": -1
        }
      ],
      "outputs": [
        {
          "name": "output"
        }
      ]
    },
    {
      "customType": "BABYLON.OneMinusBlock",
      "id": 1110,
      "name": "One minus",
      "comments": "",
      "visibleInInspector": false,
      "visibleOnFrame": false,
      "target": 4,
      "inputs": [
        {
          "name": "input",
          "inputName": "input",
          "targetBlockId": 1111,
          "targetConnectionName": "output",
          "isExposedOnFrame": true,
          "exposedPortPosition": -1
        }
      ],
      "outputs": [
        {
          "name": "output"
        }
      ]
    },
    {
      "customType": "BABYLON.ClampBlock",
      "id": 1111,
      "name": "Clamp",
      "comments": "",
      "visibleInInspector": false,
      "visibleOnFrame": false,
      "target": 4,
      "inputs": [
        {
          "name": "value",
          "inputName": "value",
          "targetBlockId": 1112,
          "targetConnectionName": "output",
          "isExposedOnFrame": true,
          "exposedPortPosition": -1
        }
      ],
      "outputs": [
        {
          "name": "output"
        }
      ],
      "minimum": 0.02,
      "maximum": 1
    },
    {
      "customType": "BABYLON.ScaleBlock",
      "id": 1112,
      "name": "rouScaleDetail",
      "comments": "",
      "visibleInInspector": false,
      "visibleOnFrame": false,
      "target": 4,
      "inputs": [
        {
          "name": "input",
          "inputName": "input",
          "targetBlockId": 1113,
          "targetConnectionName": "output",
          "isExposedOnFrame": true,
          "exposedPortPosition": -1
        },
        {
          "name": "factor",
          "inputName": "factor",
          "targetBlockId": 1121,
          "targetConnectionName": "output",
          "isExposedOnFrame": true,
          "exposedPortPosition": -1
        }
      ],
      "outputs": [
        {
          "name": "output"
        }
      ]
    },
    {
      "customType": "BABYLON.MaxBlock",
      "id": 1113,
      "name": "detailMax",
      "comments": "",
      "visibleInInspector": false,
      "visibleOnFrame": false,
      "target": 4,
      "inputs": [
        {
          "name": "left",
          "inputName": "left",
          "targetBlockId": 1114,
          "targetConnectionName": "r",
          "isExposedOnFrame": true,
          "exposedPortPosition": -1
        },
        {
          "name": "right",
          "inputName": "right",
          "targetBlockId": 1119,
          "targetConnectionName": "output",
          "isExposedOnFrame": true,
          "exposedPortPosition": -1
        }
      ],
      "outputs": [
        {
          "name": "output"
        }
      ]
    },
    {
      "customType": "BABYLON.TextureBlock",
      "id": 1114,
      "name": "Texture",
      "comments": "",
      "visibleInInspector": false,
      "visibleOnFrame": false,
      "target": 3,
      "inputs": [
        {
          "name": "uv",
          "inputName": "uv",
          "targetBlockId": 1115,
          "targetConnectionName": "output",
          "isExposedOnFrame": true,
          "exposedPortPosition": -1
        },
        {
          "name": "source",
          "inputName": "source",
          "targetBlockId": 1117,
          "targetConnectionName": "source",
          "isExposedOnFrame": true,
          "exposedPortPosition": -1
        },
        {
          "name": "layer"
        },
        {
          "name": "lod"
        }
      ],
      "outputs": [
        {
          "name": "rgba"
        },
        {
          "name": "rgb"
        },
        {
          "name": "r"
        },
        {
          "name": "g"
        },
        {
          "name": "b"
        },
        {
          "name": "a"
        },
        {
          "name": "level"
        }
      ],
      "convertToGammaSpace": false,
      "convertToLinearSpace": false,
      "fragmentOnly": false,
      "disableLevelMultiplication": false
    },
    {
      "customType": "BABYLON.ScaleBlock",
      "id": 1115,
      "name": "Scale",
      "comments": "",
      "visibleInInspector": false,
      "visibleOnFrame": false,
      "target": 4,
      "inputs": [
        {
          "name": "input",
          "inputName": "input",
          "targetBlockId": 1086,
          "targetConnectionName": "output",
          "isExposedOnFrame": true,
          "exposedPortPosition": -1
        },
        {
          "name": "factor",
          "inputName": "factor",
          "targetBlockId": 1116,
          "targetConnectionName": "output",
          "isExposedOnFrame": true,
          "exposedPortPosition": -1
        }
      ],
      "outputs": [
        {
          "name": "output"
        }
      ]
    },
    {
      "customType": "BABYLON.InputBlock",
      "id": 1116,
      "name": "detailScale",
      "comments": "",
      "visibleInInspector": true,
      "visibleOnFrame": true,
      "target": 1,
      "inputs": [],
      "outputs": [
        {
          "name": "output"
        }
      ],
      "type": 1,
      "mode": 0,
      "animationType": 0,
      "min": 0,
      "max": 0,
      "isBoolean": false,
      "matrixMode": 0,
      "isConstant": false,
      "groupInInspector": "",
      "convertToGammaSpace": false,
      "convertToLinearSpace": false,
      "valueType": "number",
      "value": 24.625
    },
    {
      "customType": "BABYLON.ImageSourceBlock",
      "id": 1117,
      "name": "detailTexture",
      "comments": "",
      "visibleInInspector": false,
      "visibleOnFrame": false,
      "target": 3,
      "inputs": [],
      "outputs": [
        {
          "name": "source"
        }
      ]
    },
    {
      "customType": "BABYLON.OneMinusBlock",
      "id": 1119,
      "name": "One minus",
      "comments": "",
      "visibleInInspector": false,
      "visibleOnFrame": false,
      "target": 4,
      "inputs": [
        {
          "name": "input",
          "inputName": "input",
          "targetBlockId": 1120,
          "targetConnectionName": "output",
          "isExposedOnFrame": true,
          "exposedPortPosition": -1
        }
      ],
      "outputs": [
        {
          "name": "output"
        }
      ]
    },
    {
      "customType": "BABYLON.InputBlock",
      "id": 1120,
      "name": "detialIntensity",
      "comments": "",
      "visibleInInspector": true,
      "visibleOnFrame": true,
      "target": 1,
      "inputs": [],
      "outputs": [
        {
          "name": "output"
        }
      ],
      "type": 1,
      "mode": 0,
      "animationType": 0,
      "min": 0,
      "max": 1,
      "isBoolean": false,
      "matrixMode": 0,
      "isConstant": false,
      "groupInInspector": "",
      "convertToGammaSpace": false,
      "convertToLinearSpace": false,
      "valueType": "number",
      "value": 1
    },
    {
      "customType": "BABYLON.LerpBlock",
      "id": 1121,
      "name": "rouTexShift",
      "comments": "",
      "visibleInInspector": false,
      "visibleOnFrame": false,
      "target": 4,
      "inputs": [
        {
          "name": "left",
          "inputName": "left",
          "targetBlockId": 1122,
          "targetConnectionName": "output",
          "isExposedOnFrame": true,
          "exposedPortPosition": -1
        },
        {
          "name": "right",
          "inputName": "right",
          "targetBlockId": 1123,
          "targetConnectionName": "output",
          "isExposedOnFrame": true,
          "exposedPortPosition": -1
        },
        {
          "name": "gradient",
          "inputName": "gradient",
          "targetBlockId": 1130,
          "targetConnectionName": "output",
          "isExposedOnFrame": true,
          "exposedPortPosition": -1
        }
      ],
      "outputs": [
        {
          "name": "output"
        }
      ]
    },
    {
      "customType": "BABYLON.InputBlock",
      "id": 1122,
      "name": "roughness",
      "comments": "",
      "visibleInInspector": true,
      "visibleOnFrame": true,
      "target": 1,
      "inputs": [],
      "outputs": [
        {
          "name": "output"
        }
      ],
      "type": 1,
      "mode": 0,
      "animationType": 0,
      "min": 0,
      "max": 1,
      "isBoolean": false,
      "matrixMode": 0,
      "isConstant": false,
      "groupInInspector": "",
      "convertToGammaSpace": false,
      "convertToLinearSpace": false,
      "valueType": "number",
      "value": 0.4425
    },
    {
      "customType": "BABYLON.ScaleBlock",
      "id": 1123,
      "name": "roughnessScale",
      "comments": "",
      "visibleInInspector": false,
      "visibleOnFrame": false,
      "target": 4,
      "inputs": [
        {
          "name": "input",
          "inputName": "input",
          "targetBlockId": 1124,
          "targetConnectionName": "output",
          "isExposedOnFrame": true,
          "exposedPortPosition": -1
        },
        {
          "name": "factor",
          "inputName": "factor",
          "targetBlockId": 1129,
          "targetConnectionName": "output",
          "isExposedOnFrame": true,
          "exposedPortPosition": -1
        }
      ],
      "outputs": [
        {
          "name": "output"
        }
      ]
    },
    {
      "customType": "BABYLON.MaxBlock",
      "id": 1124,
      "name": "rouTexMax",
      "comments": "",
      "visibleInInspector": false,
      "visibleOnFrame": false,
      "target": 4,
      "inputs": [
        {
          "name": "left",
          "inputName": "left",
          "targetBlockId": 1125,
          "targetConnectionName": "g",
          "isExposedOnFrame": true,
          "exposedPortPosition": -1
        },
        {
          "name": "right",
          "inputName": "right",
          "targetBlockId": 1128,
          "targetConnectionName": "output",
          "isExposedOnFrame": true,
          "exposedPortPosition": -1
        }
      ],
      "outputs": [
        {
          "name": "output"
        }
      ]
    },
    {
      "customType": "BABYLON.TextureBlock",
      "id": 1125,
      "name": "Texture",
      "comments": "",
      "visibleInInspector": false,
      "visibleOnFrame": false,
      "target": 3,
      "inputs": [
        {
          "name": "uv",
          "inputName": "uv",
          "targetBlockId": 1086,
          "targetConnectionName": "output",
          "isExposedOnFrame": true,
          "exposedPortPosition": -1
        },
        {
          "name": "source",
          "inputName": "source",
          "targetBlockId": 1126,
          "targetConnectionName": "source",
          "isExposedOnFrame": true,
          "exposedPortPosition": -1
        },
        {
          "name": "layer"
        },
        {
          "name": "lod"
        }
      ],
      "outputs": [
        {
          "name": "rgba"
        },
        {
          "name": "rgb"
        },
        {
          "name": "r"
        },
        {
          "name": "g"
        },
        {
          "name": "b"
        },
        {
          "name": "a"
        },
        {
          "name": "level"
        }
      ],
      "convertToGammaSpace": false,
      "convertToLinearSpace": false,
      "fragmentOnly": false,
      "disableLevelMultiplication": false
    },
    {
      "customType": "BABYLON.ImageSourceBlock",
      "id": 1126,
      "name": "ARMTexture",
      "comments": "",
      "visibleInInspector": false,
      "visibleOnFrame": false,
      "target": 3,
      "inputs": [],
      "outputs": [
        {
          "name": "source"
        }
      ]
    },
    {
      "customType": "BABYLON.InputBlock",
      "id": 1128,
      "name": "roughnessTextureMax",
      "comments": "",
      "visibleInInspector": true,
      "visibleOnFrame": true,
      "target": 1,
      "inputs": [],
      "outputs": [
        {
          "name": "output"
        }
      ],
      "type": 1,
      "mode": 0,
      "animationType": 0,
      "min": 0,
      "max": 1,
      "isBoolean": false,
      "matrixMode": 0,
      "isConstant": false,
      "groupInInspector": "",
      "convertToGammaSpace": false,
      "convertToLinearSpace": false,
      "valueType": "number",
      "value": 0
    },
    {
      "customType": "BABYLON.ClampBlock",
      "id": 1129,
      "name": "Clamp",
      "comments": "",
      "visibleInInspector": false,
      "visibleOnFrame": false,
      "target": 4,
      "inputs": [
        {
          "name": "value",
          "inputName": "value",
          "targetBlockId": 1122,
          "targetConnectionName": "output",
          "isExposedOnFrame": true,
          "exposedPortPosition": -1
        }
      ],
      "outputs": [
        {
          "name": "output"
        }
      ],
      "minimum": 0,
      "maximum": 1
    },
    {
      "customType": "BABYLON.StepBlock",
      "id": 1130,
      "name": "Step",
      "comments": "",
      "visibleInInspector": false,
      "visibleOnFrame": false,
      "target": 4,
      "inputs": [
        {
          "name": "value",
          "inputName": "value",
          "targetBlockId": 1125,
          "targetConnectionName": "g",
          "isExposedOnFrame": true,
          "exposedPortPosition": -1
        },
        {
          "name": "edge",
          "inputName": "edge",
          "targetBlockId": 1131,
          "targetConnectionName": "output",
          "isExposedOnFrame": true,
          "exposedPortPosition": -1
        }
      ],
      "outputs": [
        {
          "name": "output"
        }
      ]
    },
    {
      "customType": "BABYLON.InputBlock",
      "id": 1131,
      "name": "Float",
      "comments": "",
      "visibleInInspector": false,
      "visibleOnFrame": false,
      "target": 1,
      "inputs": [],
      "outputs": [
        {
          "name": "output"
        }
      ],
      "type": 1,
      "mode": 0,
      "animationType": 0,
      "min": 0,
      "max": 0,
      "isBoolean": false,
      "matrixMode": 0,
      "isConstant": true,
      "groupInInspector": "",
      "convertToGammaSpace": false,
      "convertToLinearSpace": false,
      "valueType": "number",
      "value": 0.0001
    },
    {
      "customType": "BABYLON.InputBlock",
      "id": 1132,
      "name": "Float",
      "comments": "",
      "visibleInInspector": false,
      "visibleOnFrame": false,
      "target": 1,
      "inputs": [],
      "outputs": [
        {
          "name": "output"
        }
      ],
      "type": 1,
      "mode": 0,
      "animationType": 0,
      "min": 0,
      "max": 0,
      "isBoolean": false,
      "matrixMode": 0,
      "isConstant": true,
      "groupInInspector": "",
      "convertToGammaSpace": false,
      "convertToLinearSpace": false,
      "valueType": "number",
      "value": 1
    },
    {
      "customType": "BABYLON.InputBlock",
      "id": 1133,
      "name": "Float",
      "comments": "",
      "visibleInInspector": false,
      "visibleOnFrame": false,
      "target": 1,
      "inputs": [],
      "outputs": [
        {
          "name": "output"
        }
      ],
      "type": 1,
      "mode": 0,
      "animationType": 0,
      "min": 0,
      "max": 0,
      "isBoolean": false,
      "matrixMode": 0,
      "isConstant": true,
      "groupInInspector": "",
      "convertToGammaSpace": false,
      "convertToLinearSpace": false,
      "valueType": "number",
      "value": 1
    },
    {
      "customType": "BABYLON.ClampBlock",
      "id": 1134,
      "name": "Clamp",
      "comments": "",
      "visibleInInspector": false,
      "visibleOnFrame": false,
      "target": 4,
      "inputs": [
        {
          "name": "value",
          "inputName": "value",
          "targetBlockId": 1135,
          "targetConnectionName": "output",
          "isExposedOnFrame": true,
          "exposedPortPosition": -1
        }
      ],
      "outputs": [
        {
          "name": "output"
        }
      ],
      "minimum": 0,
      "maximum": 1
    },
    {
      "customType": "BABYLON.AddBlock",
      "id": 1135,
      "name": "Add",
      "comments": "",
      "visibleInInspector": false,
      "visibleOnFrame": false,
      "target": 4,
      "inputs": [
        {
          "name": "left",
          "inputName": "left",
          "targetBlockId": 1136,
          "targetConnectionName": "output",
          "isExposedOnFrame": true,
          "exposedPortPosition": -1
        },
        {
          "name": "right",
          "inputName": "right",
          "targetBlockId": 1161,
          "targetConnectionName": "output",
          "isExposedOnFrame": true,
          "exposedPortPosition": -1
        }
      ],
      "outputs": [
        {
          "name": "output"
        }
      ]
    },
    {
      "customType": "BABYLON.AddBlock",
      "id": 1136,
      "name": "Add",
      "comments": "",
      "visibleInInspector": false,
      "visibleOnFrame": false,
      "target": 4,
      "inputs": [
        {
          "name": "left",
          "inputName": "left",
          "targetBlockId": 1137,
          "targetConnectionName": "output",
          "isExposedOnFrame": true,
          "exposedPortPosition": -1
        },
        {
          "name": "right",
          "inputName": "right",
          "targetBlockId": 1153,
          "targetConnectionName": "output",
          "isExposedOnFrame": true,
          "exposedPortPosition": -1
        }
      ],
      "outputs": [
        {
          "name": "output"
        }
      ]
    },
    {
      "customType": "BABYLON.ScaleBlock",
      "id": 1137,
      "name": "frontScale",
      "comments": "",
      "visibleInInspector": false,
      "visibleOnFrame": false,
      "target": 4,
      "inputs": [
        {
          "name": "input",
          "inputName": "input",
          "targetBlockId": 1138,
          "targetConnectionName": "output",
          "isExposedOnFrame": true,
          "exposedPortPosition": -1
        },
        {
          "name": "factor",
          "inputName": "factor",
          "targetBlockId": 1152,
          "targetConnectionName": "output",
          "isExposedOnFrame": true,
          "exposedPortPosition": -1
        }
      ],
      "outputs": [
        {
          "name": "output"
        }
      ]
    },
    {
      "customType": "BABYLON.PowBlock",
      "id": 1138,
      "name": "Pow",
      "comments": "",
      "visibleInInspector": false,
      "visibleOnFrame": false,
      "target": 4,
      "inputs": [
        {
          "name": "value",
          "inputName": "value",
          "targetBlockId": 1139,
          "targetConnectionName": "output",
          "isExposedOnFrame": true,
          "exposedPortPosition": -1
        },
        {
          "name": "power",
          "inputName": "power",
          "targetBlockId": 1151,
          "targetConnectionName": "output",
          "isExposedOnFrame": true,
          "exposedPortPosition": -1
        }
      ],
      "outputs": [
        {
          "name": "output"
        }
      ]
    },
    {
      "customType": "BABYLON.SubtractBlock",
      "id": 1139,
      "name": "Subtract",
      "comments": "",
      "visibleInInspector": false,
      "visibleOnFrame": false,
      "target": 4,
      "inputs": [
        {
          "name": "left",
          "inputName": "left",
          "targetBlockId": 1140,
          "targetConnectionName": "output",
          "isExposedOnFrame": true,
          "exposedPortPosition": -1
        },
        {
          "name": "right",
          "inputName": "right",
          "targetBlockId": 1148,
          "targetConnectionName": "output",
          "isExposedOnFrame": true,
          "exposedPortPosition": -1
        }
      ],
      "outputs": [
        {
          "name": "output"
        }
      ]
    },
    {
      "customType": "BABYLON.SmoothStepBlock",
      "id": 1140,
      "name": "frontLight",
      "comments": "",
      "visibleInInspector": false,
      "visibleOnFrame": false,
      "target": 4,
      "inputs": [
        {
          "name": "value",
          "inputName": "value",
          "targetBlockId": 1141,
          "targetConnectionName": "output",
          "isExposedOnFrame": true,
          "exposedPortPosition": -1
        },
        {
          "name": "edge0",
          "inputName": "edge0",
          "targetBlockId": 1146,
          "targetConnectionName": "output",
          "isExposedOnFrame": true,
          "exposedPortPosition": -1
        },
        {
          "name": "edge1",
          "inputName": "edge1",
          "targetBlockId": 1147,
          "targetConnectionName": "output",
          "isExposedOnFrame": true,
          "exposedPortPosition": -1
        }
      ],
      "outputs": [
        {
          "name": "output"
        }
      ]
    },
    {
      "customType": "BABYLON.DotBlock",
      "id": 1141,
      "name": "NDotV",
      "comments": "",
      "visibleInInspector": false,
      "visibleOnFrame": false,
      "target": 4,
      "inputs": [
        {
          "name": "left",
          "inputName": "left",
          "targetBlockId": 1142,
          "targetConnectionName": "xyz",
          "isExposedOnFrame": true,
          "exposedPortPosition": -1
        },
        {
          "name": "right",
          "inputName": "right",
          "targetBlockId": 1143,
          "targetConnectionName": "output",
          "isExposedOnFrame": true,
          "exposedPortPosition": -1
        }
      ],
      "outputs": [
        {
          "name": "output"
        }
      ]
    },
    {
      "customType": "BABYLON.TransformBlock",
      "id": 1142,
      "name": "World normal",
      "comments": "",
      "visibleInInspector": false,
      "visibleOnFrame": false,
      "target": 1,
      "inputs": [
        {
          "name": "vector",
          "inputName": "vector",
          "targetBlockId": 1082,
          "targetConnectionName": "normalOutput",
          "isExposedOnFrame": true,
          "exposedPortPosition": -1
        },
        {
          "name": "transform",
          "inputName": "transform",
          "targetBlockId": 1087,
          "targetConnectionName": "output",
          "isExposedOnFrame": true,
          "exposedPortPosition": -1
        }
      ],
      "outputs": [
        {
          "name": "output"
        },
        {
          "name": "xyz"
        }
      ],
      "complementZ": 0,
      "complementW": 0
    },
    {
      "customType": "BABYLON.NormalizeBlock",
      "id": 1143,
      "name": "Normalize",
      "comments": "",
      "visibleInInspector": false,
      "visibleOnFrame": false,
      "target": 4,
      "inputs": [
        {
          "name": "input",
          "inputName": "input",
          "targetBlockId": 1144,
          "targetConnectionName": "output",
          "isExposedOnFrame": true,
          "exposedPortPosition": -1
        }
      ],
      "outputs": [
        {
          "name": "output"
        }
      ]
    },
    {
      "customType": "BABYLON.ViewDirectionBlock",
      "id": 1144,
      "name": "View direction",
      "comments": "",
      "visibleInInspector": false,
      "visibleOnFrame": false,
      "target": 4,
      "inputs": [
        {
          "name": "worldPosition",
          "inputName": "worldPosition",
          "targetBlockId": 1081,
          "targetConnectionName": "output",
          "isExposedOnFrame": true,
          "exposedPortPosition": -1
        },
        {
          "name": "cameraPosition",
          "inputName": "cameraPosition",
          "targetBlockId": 1145,
          "targetConnectionName": "output",
          "isExposedOnFrame": true,
          "exposedPortPosition": -1
        }
      ],
      "outputs": [
        {
          "name": "output"
        }
      ]
    },
    {
      "customType": "BABYLON.InputBlock",
      "id": 1145,
      "name": "cameraPosition",
      "comments": "",
      "visibleInInspector": false,
      "visibleOnFrame": false,
      "target": 1,
      "inputs": [],
      "outputs": [
        {
          "name": "output"
        }
      ],
      "type": 8,
      "mode": 0,
      "systemValue": 7,
      "animationType": 0,
      "min": 0,
      "max": 0,
      "isBoolean": false,
      "matrixMode": 0,
      "isConstant": false,
      "groupInInspector": "",
      "convertToGammaSpace": false,
      "convertToLinearSpace": false
    },
    {
      "customType": "BABYLON.ClampBlock",
      "id": 1146,
      "name": "Clamp",
      "comments": "",
      "visibleInInspector": false,
      "visibleOnFrame": false,
      "target": 4,
      "inputs": [
        {
          "name": "value",
          "inputName": "value",
          "targetBlockId": 1110,
          "targetConnectionName": "output",
          "isExposedOnFrame": true,
          "exposedPortPosition": -1
        }
      ],
      "outputs": [
        {
          "name": "output"
        }
      ],
      "minimum": 0,
      "maximum": 1
    },
    {
      "customType": "BABYLON.InputBlock",
      "id": 1147,
      "name": "Float",
      "comments": "",
      "visibleInInspector": false,
      "visibleOnFrame": false,
      "target": 1,
      "inputs": [],
      "outputs": [
        {
          "name": "output"
        }
      ],
      "type": 1,
      "mode": 0,
      "animationType": 0,
      "min": 0,
      "max": 1,
      "isBoolean": false,
      "matrixMode": 0,
      "isConstant": true,
      "groupInInspector": "",
      "convertToGammaSpace": false,
      "convertToLinearSpace": false,
      "valueType": "number",
      "value": 1
    },
    {
      "customType": "BABYLON.ScaleBlock",
      "id": 1148,
      "name": "Scale",
      "comments": "",
      "visibleInInspector": false,
      "visibleOnFrame": false,
      "target": 4,
      "inputs": [
        {
          "name": "input",
          "inputName": "input",
          "targetBlockId": 1149,
          "targetConnectionName": "output",
          "isExposedOnFrame": true,
          "exposedPortPosition": -1
        },
        {
          "name": "factor",
          "inputName": "factor",
          "targetBlockId": 1120,
          "targetConnectionName": "output",
          "isExposedOnFrame": true,
          "exposedPortPosition": -1
        }
      ],
      "outputs": [
        {
          "name": "output"
        }
      ]
    },
    {
      "customType": "BABYLON.LerpBlock",
      "id": 1149,
      "name": "Lerp",
      "comments": "",
      "visibleInInspector": false,
      "visibleOnFrame": false,
      "target": 4,
      "inputs": [
        {
          "name": "left",
          "inputName": "left",
          "targetBlockId": 1150,
          "targetConnectionName": "output",
          "isExposedOnFrame": true,
          "exposedPortPosition": -1
        },
        {
          "name": "right",
          "inputName": "right",
          "targetBlockId": 5087,
          "targetConnectionName": "output",
          "isExposedOnFrame": true,
          "exposedPortPosition": -1
        },
        {
          "name": "gradient",
          "inputName": "gradient",
          "targetBlockId": 1140,
          "targetConnectionName": "output",
          "isExposedOnFrame": true,
          "exposedPortPosition": -1
        }
      ],
      "outputs": [
        {
          "name": "output"
        }
      ]
    },
    {
      "customType": "BABYLON.InputBlock",
      "id": 1150,
      "name": "Float",
      "comments": "",
      "visibleInInspector": false,
      "visibleOnFrame": false,
      "target": 1,
      "inputs": [],
      "outputs": [
        {
          "name": "output"
        }
      ],
      "type": 1,
      "mode": 0,
      "animationType": 0,
      "min": 0,
      "max": 0,
      "isBoolean": false,
      "matrixMode": 0,
      "isConstant": true,
      "groupInInspector": "",
      "convertToGammaSpace": false,
      "convertToLinearSpace": false,
      "valueType": "number",
      "value": 0
    },
    {
      "customType": "BABYLON.RemapBlock",
      "id": 5087,
      "name": "Remap",
      "comments": "",
      "visibleInInspector": false,
      "visibleOnFrame": false,
      "target": 4,
      "inputs": [
        {
          "name": "input",
          "inputName": "input",
          "targetBlockId": 1114,
          "targetConnectionName": "g",
          "isExposedOnFrame": true,
          "exposedPortPosition": -1
        },
        {
          "name": "sourceMin"
        },
        {
          "name": "sourceMax"
        },
        {
          "name": "targetMin"
        },
        {
          "name": "targetMax"
        }
      ],
      "outputs": [
        {
          "name": "output"
        }
      ],
      "sourceRange": [
        0.1,
        0.2
      ],
      "targetRange": [
        0,
        0.6
      ]
    },
    {
      "customType": "BABYLON.InputBlock",
      "id": 1151,
      "name": "Float",
      "comments": "",
      "visibleInInspector": false,
      "visibleOnFrame": false,
      "target": 1,
      "inputs": [],
      "outputs": [
        {
          "name": "output"
        }
      ],
      "type": 1,
      "mode": 0,
      "animationType": 0,
      "min": 0,
      "max": 2,
      "isBoolean": false,
      "matrixMode": 0,
      "isConstant": true,
      "groupInInspector": "",
      "convertToGammaSpace": false,
      "convertToLinearSpace": false,
      "valueType": "number",
      "value": 2
    },
    {
      "customType": "BABYLON.InputBlock",
      "id": 1152,
      "name": "frontIntensity",
      "comments": "",
      "visibleInInspector": true,
      "visibleOnFrame": true,
      "target": 1,
      "inputs": [],
      "outputs": [
        {
          "name": "output"
        }
      ],
      "type": 1,
      "mode": 0,
      "animationType": 0,
      "min": 0,
      "max": 1,
      "isBoolean": false,
      "matrixMode": 0,
      "isConstant": false,
      "groupInInspector": "",
      "convertToGammaSpace": false,
      "convertToLinearSpace": false,
      "valueType": "number",
      "value": 0.3025
    },
    {
      "customType": "BABYLON.ScaleBlock",
      "id": 1153,
      "name": "rimScale",
      "comments": "",
      "visibleInInspector": false,
      "visibleOnFrame": false,
      "target": 4,
      "inputs": [
        {
          "name": "input",
          "displayName": "input",
          "inputName": "input",
          "targetBlockId": 1154,
          "targetConnectionName": "output",
          "isExposedOnFrame": true,
          "exposedPortPosition": 0
        },
        {
          "name": "factor",
          "displayName": "factor",
          "inputName": "factor",
          "targetBlockId": 1155,
          "targetConnectionName": "output",
          "isExposedOnFrame": true,
          "exposedPortPosition": -1
        }
      ],
      "outputs": [
        {
          "name": "output",
          "displayName": "output",
          "isExposedOnFrame": true,
          "exposedPortPosition": 0
        }
      ]
    },
    {
      "customType": "BABYLON.InputBlock",
      "id": 1154,
      "name": "rimIntensity",
      "comments": "",
      "visibleInInspector": true,
      "visibleOnFrame": true,
      "target": 1,
      "inputs": [],
      "outputs": [
        {
          "name": "output"
        }
      ],
      "type": 1,
      "mode": 0,
      "animationType": 0,
      "min": 0,
      "max": 1,
      "isBoolean": false,
      "matrixMode": 0,
      "isConstant": false,
      "groupInInspector": "",
      "convertToGammaSpace": false,
      "convertToLinearSpace": false,
      "valueType": "number",
      "value": 0.5525
    },
    {
      "customType": "BABYLON.OneMinusBlock",
      "id": 1155,
      "name": "fresnel",
      "comments": "",
      "visibleInInspector": false,
      "visibleOnFrame": false,
      "target": 4,
      "inputs": [
        {
          "name": "input",
          "displayName": "input",
          "inputName": "input",
          "targetBlockId": 1156,
          "targetConnectionName": "output",
          "isExposedOnFrame": true,
          "exposedPortPosition": -1
        }
      ],
      "outputs": [
        {
          "name": "output",
          "displayName": "output"
        }
      ]
    },
    {
      "customType": "BABYLON.SmoothStepBlock",
      "id": 1156,
      "name": "facing",
      "comments": "",
      "visibleInInspector": false,
      "visibleOnFrame": false,
      "target": 4,
      "inputs": [
        {
          "name": "value",
          "displayName": "value",
          "inputName": "value",
          "targetBlockId": 1141,
          "targetConnectionName": "output",
          "isExposedOnFrame": true,
          "exposedPortPosition": 1
        },
        {
          "name": "edge0",
          "displayName": "edge0",
          "inputName": "edge0",
          "targetBlockId": 1157,
          "targetConnectionName": "output",
          "isExposedOnFrame": true,
          "exposedPortPosition": -1
        },
        {
          "name": "edge1",
          "displayName": "edge1",
          "inputName": "edge1",
          "targetBlockId": 1158,
          "targetConnectionName": "output",
          "isExposedOnFrame": true,
          "exposedPortPosition": 2
        }
      ],
      "outputs": [
        {
          "name": "output",
          "displayName": "output"
        }
      ]
    },
    {
      "customType": "BABYLON.InputBlock",
      "id": 1157,
      "name": "Float",
      "comments": "",
      "visibleInInspector": false,
      "visibleOnFrame": false,
      "target": 1,
      "inputs": [],
      "outputs": [
        {
          "name": "output"
        }
      ],
      "type": 1,
      "mode": 0,
      "animationType": 0,
      "min": 0,
      "max": 1,
      "isBoolean": false,
      "matrixMode": 0,
      "isConstant": true,
      "groupInInspector": "",
      "convertToGammaSpace": false,
      "convertToLinearSpace": false,
      "valueType": "number",
      "value": 0
    },
    {
      "customType": "BABYLON.PowBlock",
      "id": 1158,
      "name": "Pow",
      "comments": "",
      "visibleInInspector": false,
      "visibleOnFrame": false,
      "target": 4,
      "inputs": [
        {
          "name": "value",
          "inputName": "value",
          "targetBlockId": 1159,
          "targetConnectionName": "output",
          "isExposedOnFrame": true,
          "exposedPortPosition": -1
        },
        {
          "name": "power",
          "inputName": "power",
          "targetBlockId": 1160,
          "targetConnectionName": "output",
          "isExposedOnFrame": true,
          "exposedPortPosition": -1
        }
      ],
      "outputs": [
        {
          "name": "output"
        }
      ]
    },
    {
      "customType": "BABYLON.OneMinusBlock",
      "id": 1159,
      "name": "One minus",
      "comments": "",
      "visibleInInspector": false,
      "visibleOnFrame": false,
      "target": 4,
      "inputs": [
        {
          "name": "input",
          "displayName": "input",
          "inputName": "input",
          "targetBlockId": 1146,
          "targetConnectionName": "output",
          "isExposedOnFrame": true,
          "exposedPortPosition": 3
        }
      ],
      "outputs": [
        {
          "name": "output",
          "displayName": "output",
          "isExposedOnFrame": true,
          "exposedPortPosition": 1
        }
      ]
    },
    {
      "customType": "BABYLON.InputBlock",
      "id": 1160,
      "name": "Float",
      "comments": "",
      "visibleInInspector": false,
      "visibleOnFrame": false,
      "target": 1,
      "inputs": [],
      "outputs": [
        {
          "name": "output"
        }
      ],
      "type": 1,
      "mode": 0,
      "animationType": 0,
      "min": 0,
      "max": 2,
      "isBoolean": false,
      "matrixMode": 0,
      "isConstant": true,
      "groupInInspector": "",
      "convertToGammaSpace": false,
      "convertToLinearSpace": false,
      "valueType": "number",
      "value": 0.35
    },
    {
      "customType": "BABYLON.ScaleBlock",
      "id": 1161,
      "name": "topScale",
      "comments": "",
      "visibleInInspector": false,
      "visibleOnFrame": false,
      "target": 4,
      "inputs": [
        {
          "name": "input",
          "inputName": "input",
          "targetBlockId": 1162,
          "targetConnectionName": "output",
          "isExposedOnFrame": true,
          "exposedPortPosition": -1
        },
        {
          "name": "factor",
          "inputName": "factor",
          "targetBlockId": 1171,
          "targetConnectionName": "output",
          "isExposedOnFrame": true,
          "exposedPortPosition": -1
        }
      ],
      "outputs": [
        {
          "name": "output"
        }
      ]
    },
    {
      "customType": "BABYLON.DivideBlock",
      "id": 1162,
      "name": "Divide",
      "comments": "",
      "visibleInInspector": false,
      "visibleOnFrame": false,
      "target": 4,
      "inputs": [
        {
          "name": "left",
          "inputName": "left",
          "targetBlockId": 1163,
          "targetConnectionName": "output",
          "isExposedOnFrame": true,
          "exposedPortPosition": -1
        },
        {
          "name": "right",
          "inputName": "right",
          "targetBlockId": 1170,
          "targetConnectionName": "output",
          "isExposedOnFrame": true,
          "exposedPortPosition": -1
        }
      ],
      "outputs": [
        {
          "name": "output"
        }
      ]
    },
    {
      "customType": "BABYLON.AddBlock",
      "id": 1163,
      "name": "Add",
      "comments": "",
      "visibleInInspector": false,
      "visibleOnFrame": false,
      "target": 4,
      "inputs": [
        {
          "name": "left",
          "inputName": "left",
          "targetBlockId": 1164,
          "targetConnectionName": "output",
          "isExposedOnFrame": true,
          "exposedPortPosition": -1
        },
        {
          "name": "right",
          "inputName": "right",
          "targetBlockId": 1169,
          "targetConnectionName": "output",
          "isExposedOnFrame": true,
          "exposedPortPosition": -1
        }
      ],
      "outputs": [
        {
          "name": "output"
        }
      ]
    },
    {
      "customType": "BABYLON.DotBlock",
      "id": 1164,
      "name": "topLight",
      "comments": "",
      "visibleInInspector": false,
      "visibleOnFrame": false,
      "target": 4,
      "inputs": [
        {
          "name": "left",
          "inputName": "left",
          "targetBlockId": 1142,
          "targetConnectionName": "xyz",
          "isExposedOnFrame": true,
          "exposedPortPosition": -1
        },
        {
          "name": "right",
          "inputName": "right",
          "targetBlockId": 1165,
          "targetConnectionName": "xyz",
          "isExposedOnFrame": true,
          "exposedPortPosition": -1
        }
      ],
      "outputs": [
        {
          "name": "output"
        }
      ]
    },
    {
      "customType": "BABYLON.VectorMergerBlock",
      "id": 1165,
      "name": "VectorMerger",
      "comments": "",
      "visibleInInspector": false,
      "visibleOnFrame": false,
      "target": 4,
      "inputs": [
        {
          "name": "xyzw "
        },
        {
          "name": "xyz "
        },
        {
          "name": "xy "
        },
        {
          "name": "zw "
        },
        {
          "name": "x",
          "inputName": "x",
          "targetBlockId": 1166,
          "targetConnectionName": "output",
          "isExposedOnFrame": true,
          "exposedPortPosition": -1
        },
        {
          "name": "y",
          "inputName": "y",
          "targetBlockId": 1167,
          "targetConnectionName": "output",
          "isExposedOnFrame": true,
          "exposedPortPosition": -1
        },
        {
          "name": "z",
          "inputName": "z",
          "targetBlockId": 1168,
          "targetConnectionName": "output",
          "isExposedOnFrame": true,
          "exposedPortPosition": -1
        },
        {
          "name": "w"
        }
      ],
      "outputs": [
        {
          "name": "xyzw"
        },
        {
          "name": "xyz"
        },
        {
          "name": "xy"
        },
        {
          "name": "zw"
        }
      ],
      "xSwizzle": "x",
      "ySwizzle": "y",
      "zSwizzle": "z",
      "wSwizzle": "w"
    },
    {
      "customType": "BABYLON.InputBlock",
      "id": 1166,
      "name": "Float",
      "comments": "",
      "visibleInInspector": false,
      "visibleOnFrame": false,
      "target": 1,
      "inputs": [],
      "outputs": [
        {
          "name": "output"
        }
      ],
      "type": 1,
      "mode": 0,
      "animationType": 0,
      "min": 0,
      "max": 0,
      "isBoolean": false,
      "matrixMode": 0,
      "isConstant": true,
      "groupInInspector": "",
      "convertToGammaSpace": false,
      "convertToLinearSpace": false,
      "valueType": "number",
      "value": 0
    },
    {
      "customType": "BABYLON.InputBlock",
      "id": 1167,
      "name": "Float",
      "comments": "",
      "visibleInInspector": false,
      "visibleOnFrame": false,
      "target": 1,
      "inputs": [],
      "outputs": [
        {
          "name": "output"
        }
      ],
      "type": 1,
      "mode": 0,
      "animationType": 0,
      "min": 0,
      "max": 0,
      "isBoolean": false,
      "matrixMode": 0,
      "isConstant": true,
      "groupInInspector": "",
      "convertToGammaSpace": false,
      "convertToLinearSpace": false,
      "valueType": "number",
      "value": 1
    },
    {
      "customType": "BABYLON.InputBlock",
      "id": 1168,
      "name": "Float",
      "comments": "",
      "visibleInInspector": false,
      "visibleOnFrame": false,
      "target": 1,
      "inputs": [],
      "outputs": [
        {
          "name": "output"
        }
      ],
      "type": 1,
      "mode": 0,
      "animationType": 0,
      "min": 0,
      "max": 0,
      "isBoolean": false,
      "matrixMode": 0,
      "isConstant": true,
      "groupInInspector": "",
      "convertToGammaSpace": false,
      "convertToLinearSpace": false,
      "valueType": "number",
      "value": 0
    },
    {
      "customType": "BABYLON.InputBlock",
      "id": 1169,
      "name": "Float",
      "comments": "",
      "visibleInInspector": false,
      "visibleOnFrame": false,
      "target": 1,
      "inputs": [],
      "outputs": [
        {
          "name": "output"
        }
      ],
      "type": 1,
      "mode": 0,
      "animationType": 0,
      "min": 0,
      "max": 0,
      "isBoolean": false,
      "matrixMode": 0,
      "isConstant": true,
      "groupInInspector": "",
      "convertToGammaSpace": false,
      "convertToLinearSpace": false,
      "valueType": "number",
      "value": 1
    },
    {
      "customType": "BABYLON.InputBlock",
      "id": 1170,
      "name": "Float",
      "comments": "",
      "visibleInInspector": false,
      "visibleOnFrame": false,
      "target": 1,
      "inputs": [],
      "outputs": [
        {
          "name": "output"
        }
      ],
      "type": 1,
      "mode": 0,
      "animationType": 0,
      "min": 0,
      "max": 0,
      "isBoolean": false,
      "matrixMode": 0,
      "isConstant": true,
      "groupInInspector": "",
      "convertToGammaSpace": false,
      "convertToLinearSpace": false,
      "valueType": "number",
      "value": 2
    },
    {
      "customType": "BABYLON.InputBlock",
      "id": 1171,
      "name": "topIntensity",
      "comments": "",
      "visibleInInspector": true,
      "visibleOnFrame": true,
      "target": 1,
      "inputs": [],
      "outputs": [
        {
          "name": "output"
        }
      ],
      "type": 1,
      "mode": 0,
      "animationType": 0,
      "min": 0,
      "max": 1,
      "isBoolean": false,
      "matrixMode": 0,
      "isConstant": false,
      "groupInInspector": "",
      "convertToGammaSpace": false,
      "convertToLinearSpace": false,
      "valueType": "number",
      "value": 0.17
    },
    {
      "customType": "BABYLON.LerpBlock",
      "id": 1172,
      "name": "AOTexShift",
      "comments": "",
      "visibleInInspector": false,
      "visibleOnFrame": false,
      "target": 4,
      "inputs": [
        {
          "name": "left",
          "inputName": "left",
          "targetBlockId": 1173,
          "targetConnectionName": "output",
          "isExposedOnFrame": true,
          "exposedPortPosition": -1
        },
        {
          "name": "right",
          "inputName": "right",
          "targetBlockId": 1125,
          "targetConnectionName": "r",
          "isExposedOnFrame": true,
          "exposedPortPosition": -1
        },
        {
          "name": "gradient",
          "inputName": "gradient",
          "targetBlockId": 1174,
          "targetConnectionName": "output",
          "isExposedOnFrame": true,
          "exposedPortPosition": -1
        }
      ],
      "outputs": [
        {
          "name": "output"
        }
      ]
    },
    {
      "customType": "BABYLON.InputBlock",
      "id": 1173,
      "name": "Float",
      "comments": "",
      "visibleInInspector": false,
      "visibleOnFrame": false,
      "target": 1,
      "inputs": [],
      "outputs": [
        {
          "name": "output"
        }
      ],
      "type": 1,
      "mode": 0,
      "animationType": 0,
      "min": 0,
      "max": 0,
      "isBoolean": false,
      "matrixMode": 0,
      "isConstant": true,
      "groupInInspector": "",
      "convertToGammaSpace": false,
      "convertToLinearSpace": false,
      "valueType": "number",
      "value": 1
    },
    {
      "customType": "BABYLON.ScaleBlock",
      "id": 1174,
      "name": "AOScale",
      "comments": "",
      "visibleInInspector": false,
      "visibleOnFrame": false,
      "target": 4,
      "inputs": [
        {
          "name": "input",
          "inputName": "input",
          "targetBlockId": 1175,
          "targetConnectionName": "output",
          "isExposedOnFrame": true,
          "exposedPortPosition": -1
        },
        {
          "name": "factor",
          "inputName": "factor",
          "targetBlockId": 1177,
          "targetConnectionName": "output",
          "isExposedOnFrame": true,
          "exposedPortPosition": -1
        }
      ],
      "outputs": [
        {
          "name": "output"
        }
      ]
    },
    {
      "customType": "BABYLON.StepBlock",
      "id": 1175,
      "name": "Step",
      "comments": "",
      "visibleInInspector": false,
      "visibleOnFrame": false,
      "target": 4,
      "inputs": [
        {
          "name": "value",
          "inputName": "value",
          "targetBlockId": 1125,
          "targetConnectionName": "r",
          "isExposedOnFrame": true,
          "exposedPortPosition": -1
        },
        {
          "name": "edge",
          "inputName": "edge",
          "targetBlockId": 1176,
          "targetConnectionName": "output",
          "isExposedOnFrame": true,
          "exposedPortPosition": -1
        }
      ],
      "outputs": [
        {
          "name": "output"
        }
      ]
    },
    {
      "customType": "BABYLON.InputBlock",
      "id": 1176,
      "name": "Float",
      "comments": "",
      "visibleInInspector": false,
      "visibleOnFrame": false,
      "target": 1,
      "inputs": [],
      "outputs": [
        {
          "name": "output"
        }
      ],
      "type": 1,
      "mode": 0,
      "animationType": 0,
      "min": 0,
      "max": 0,
      "isBoolean": false,
      "matrixMode": 0,
      "isConstant": true,
      "groupInInspector": "",
      "convertToGammaSpace": false,
      "convertToLinearSpace": false,
      "valueType": "number",
      "value": 0.0001
    },
    {
      "customType": "BABYLON.InputBlock",
      "id": 1177,
      "name": "AOIntensity",
      "comments": "",
      "visibleInInspector": true,
      "visibleOnFrame": true,
      "target": 1,
      "inputs": [],
      "outputs": [
        {
          "name": "output"
        }
      ],
      "type": 1,
      "mode": 0,
      "animationType": 0,
      "min": 0,
      "max": 1,
      "isBoolean": false,
      "matrixMode": 0,
      "isConstant": false,
      "groupInInspector": "",
      "convertToGammaSpace": false,
      "convertToLinearSpace": false,
      "valueType": "number",
      "value": 1
    }
  ]
}